webhookpy/__init__.py
webhookpy/command.py
webhookpy/config.py
webhookpy/errors.py
webhookpy/slack_webhook.py
webhookpy-0.1.0.dist-info/LICENSE
webhookpy-0.1.0.dist-info/METADATA
webhookpy-0.1.0.dist-info/WHEEL
webhookpy-0.1.0.dist-info/entry_points.txt
webhookpy-0.1.0.dist-info/RECORD
